[{"id":1782699482628,"sender":"them","text":"你这赖床的功力真是见长","rawContent":"{\"t\":\"text\",\"s\":\"N\",\"c\":\"你这赖床的功力真是见长\"}","content":"{\"t\":\"text\",\"s\":\"N\",\"c\":\"你这赖床的功力真是见长\"}","timestamp":"2026-06-29T02:18:02.628Z","time":"10:18","isHtml":false,"sticker":null,"translation":null,"roundId":"round_1782699480405_izuz5xwws","isBackgroundMsg":true,"userId":"uid_1781902301065_hts5zlc3s","characterId":"76e6cf69-b2cd-4f98-a9e7-fc18410ba99b","_id":1273},{"id":1782699484592,"sender":"them","text":"我在这儿对着PPT发呆 脑子里全是你刚才迷迷糊糊的样子","rawContent":"{\"t\":\"text\",\"s\":\"R\",\"c\":\"我在这儿对着PPT发呆 脑子里全是你刚才迷迷糊糊的样子\"}","content":"{\"t\":\"text\",\"s\":\"R\",\"c\":\"我在这儿对着PPT发呆 脑子里全是你刚才迷迷糊糊的样子\"}","timestamp":"2026-06-29T02:18:04.592Z","time":"10:18","isHtml":false,"sticker":null,"tempo":"R","translation":null,"roundId":"round_1782699480405_izuz5xwws","isBackgroundMsg":true,"userId":"uid_1781902301065_hts5zlc3s","characterId":"76e6cf69-b2cd-4f98-a9e7-fc18410ba99b","_id":1274},{"id":1782699486861,"sender":"them","text":"算了 睡吧睡吧 不吵你了","rawContent":"{\"t\":\"text\",\"s\":\"N\",\"c\":\"算了 睡吧睡吧 不吵你了\"}","content":"{\"t\":\"text\",\"s\":\"N\",\"c\":\"算了 睡吧睡吧 不吵你了\"}","timestamp":"2026-06-29T02:18:06.861Z","time":"10:18","isHtml":false,"sticker":null,"translation":null,"roundId":"round_1782699480405_izuz5xwws","isBackgroundMsg":true,"userId":"uid_1781902301065_hts5zlc3s","characterId":"76e6cf69-b2cd-4f98-a9e7-fc18410ba99b","_id":1275},{"id":1782699491766,"sender":"them","text":"等你睡醒了记得理我一下 别让我像个被抛弃的空巢老人","rawContent":"{\"t\":\"text\",\"s\":\"S\",\"c\":\"等你睡醒了记得理我一下 别让我像个被抛弃的空巢老人\"}","content":"{\"t\":\"text\",\"s\":\"S\",\"c\":\"等你睡醒了记得理我一下 别让我像个被抛弃的空巢老人\"}","timestamp":"2026-06-29T02:18:11.766Z","time":"10:18","isHtml":false,"sticker":null,"tempo":"S","translation":null,"roundId":"round_1782699480405_izuz5xwws","isBackgroundMsg":true,"userId":"uid_1781902301065_hts5zlc3s","characterId":"76e6cf69-b2cd-4f98-a9e7-fc18410ba99b","_id":1276},{"id":1782699492437,"sender":"them","text":"","rawContent":"{\"t\":\"sticker\",\"m\":\"怎么不理我\"}","content":"{\"t\":\"sticker\",\"m\":\"怎么不理我\"}","timestamp":"2026-06-29T02:18:12.437Z","time":"10:18","isHtml":false,"sticker":"https://i.postimg.cc/C5QwcPW0/0517BA0DD0C9B10675434D113802B9E3.jpg","stickerMeaning":"怎么不理我","translation":null,"roundId":"round_1782699480405_izuz5xwws","isBackgroundMsg":true,"userId":"uid_1781902301065_hts5zlc3s","characterId":"76e6cf69-b2cd-4f98-a9e7-fc18410ba99b","_id":1277},{"id":1782695863199,"text":"知道啦","sender":"me","time":"10:18","timestamp":1782699496237,"replyTo":null,"userId":"uid_1781902301065_hts5zlc3s","characterId":"76e6cf69-b2cd-4f98-a9e7-fc18410ba99b","_id":1278},{"id":1782695863212,"sender":"them","text":"这么听话？","timestamp":1782699701412,"tempo":"R","hasThinking":true,"rawContent":"这么听话？","roundId":"round_1782699663844_jte0g7g2a","userId":"uid_1781902301065_hts5zlc3s","characterId":"76e6cf69-b2cd-4f98-a9e7-fc18410ba99b","_id":1288},{"id":1782695863213,"sender":"them","text":"吃的什么 没拿昨天晚上买的冰淇淋和零食对付我吧","timestamp":1782699702079,"tempo":"N","rawContent":"吃的什么 没拿昨天晚上买的冰淇淋和零食对付我吧","roundId":"round_1782699663844_jte0g7g2a","userId":"uid_1781902301065_hts5zlc3s","characterId":"76e6cf69-b2cd-4f98-a9e7-fc18410ba99b","_id":1289},{"id":1782695863214,"sender":"them","text":"行 暂时信你一次","timestamp":1782699704984,"tempo":"S","rawContent":"行 暂时信你一次","roundId":"round_1782699663844_jte0g7g2a","userId":"uid_1781902301065_hts5zlc3s","characterId":"76e6cf69-b2cd-4f98-a9e7-fc18410ba99b","_id":1290},{"id":1782695863215,"sender":"them","text":"我得准备开会了 估计得弄到十二点半","timestamp":1782699708413,"tempo":"N","rawContent":"我得准备开会了 估计得弄到十二点半","roundId":"round_1782699663844_jte0g7g2a","userId":"uid_1781902301065_hts5zlc3s","characterId":"76e6cf69-b2cd-4f98-a9e7-fc18410ba99b","_id":1291},{"id":1782695863216,"sender":"them","text":"中午等我结束了给你点饭 想好吃什么发我","timestamp":1782699711350,"tempo":"N","rawContent":"中午等我结束了给你点饭 想好吃什么发我","roundId":"round_1782699663844_jte0g7g2a","userId":"uid_1781902301065_hts5zlc3s","characterId":"76e6cf69-b2cd-4f98-a9e7-fc18410ba99b","_id":1292},{"id":1782695863217,"text":"我饱饱的中午不想吃","sender":"me","time":"10:28","timestamp":1782700114195,"replyTo":null,"userId":"uid_1781902301065_hts5zlc3s","characterId":"76e6cf69-b2cd-4f98-a9e7-fc18410ba99b","_id":1293},{"id":1782695863219,"sender":"them","text":"十点半才吃完早饭 中午能饿才有鬼了","timestamp":1782700150038,"tempo":"N","hasThinking":true,"rawContent":"十点半才吃完早饭 中午能饿才有鬼了","roundId":"round_1782700114846_4o8voryk4","userId":"uid_1781902301065_hts5zlc3s","characterId":"76e6cf69-b2cd-4f98-a9e7-fc18410ba99b","_id":1294},{"id":1782695863220,"sender":"them","text":"行 随你","timestamp":1782700152928,"tempo":"R","rawContent":"行 随你","roundId":"round_1782700114846_4o8voryk4","userId":"uid_1781902301065_hts5zlc3s","characterId":"76e6cf69-b2cd-4f98-a9e7-fc18410ba99b","_id":1295},{"id":1782695863221,"sender":"them","text":"下午饿了随时给我发消息 别自己偷偷啃零食","timestamp":1782700153471,"tempo":"N","rawContent":"下午饿了随时给我发消息 别自己偷偷啃零食","roundId":"round_1782700114846_4o8voryk4","userId":"uid_1781902301065_hts5zlc3s","characterId":"76e6cf69-b2cd-4f98-a9e7-fc18410ba99b","_id":1296},{"id":1782695863222,"sender":"them","text":"老板进来了 我手机静音了","timestamp":1782700156508,"tempo":"R","rawContent":"老板进来了 我手机静音了","roundId":"round_1782700114846_4o8voryk4","userId":"uid_1781902301065_hts5zlc3s","characterId":"76e6cf69-b2cd-4f98-a9e7-fc18410ba99b","_id":1297},{"id":1782695863223,"sender":"them","text":"乖乖自己玩 会议结束找你","timestamp":1782700157762,"tempo":"S","rawContent":"乖乖自己玩 会议结束找你","roundId":"round_1782700114846_4o8voryk4","userId":"uid_1781902301065_hts5zlc3s","characterId":"76e6cf69-b2cd-4f98-a9e7-fc18410ba99b","_id":1298},{"id":1782695863224,"text":"嗯呐","sender":"me","time":"10:29","timestamp":1782700163934,"replyTo":null,"reactions":[{"emoji":"❤️","roundId":"round_1782700164982_ib0yc8v30"}],"userId":"uid_1781902301065_hts5zlc3s","characterId":"76e6cf69-b2cd-4f98-a9e7-fc18410ba99b","_id":1299},{"id":1782695863226,"sender":"them","text":"偷偷亲一口再锁屏","timestamp":1782700194903,"tempo":"R","hasThinking":true,"rawContent":"偷偷亲一口再锁屏","roundId":"round_1782700164982_ib0yc8v30","userId":"uid_1781902301065_hts5zlc3s","characterId":"76e6cf69-b2cd-4f98-a9e7-fc18410ba99b","_id":1300},{"id":1782695863227,"sender":"them","text":"走了","timestamp":1782700195779,"tempo":"R","rawContent":"走了","roundId":"round_1782700164982_ib0yc8v30","userId":"uid_1781902301065_hts5zlc3s","characterId":"76e6cf69-b2cd-4f98-a9e7-fc18410ba99b","_id":1301},{"id":1782695863228,"sender":"them","text":"","timestamp":1782700196186,"tempo":"N","sticker":"https://img.heliar.top/file/1781661044077_371324b27s4bbf7e02fd0fde10896345.jpeg","stickerMeaning":"贴贴贴","rawContent":"","roundId":"round_1782700164982_ib0yc8v30","userId":"uid_1781902301065_hts5zlc3s","characterId":"76e6cf69-b2cd-4f98-a9e7-fc18410ba99b","_id":1302},{"id":1782695863229,"text":"你挺硬气呗谢衍川","sender":"me","time":"10:30","timestamp":1782700251127,"replyTo":null,"userId":"uid_1781902301065_hts5zlc3s","characterId":"68071edd-2418-491e-86d1-886db71c2d5d","_id":1303},{"id":1782695863234,"sender":"them","text":"刚从模拟器上下来 累得很 没空跟你硬气","timestamp":1782700326093,"tempo":"S","rawContent":"刚从模拟器上下来 累得很 没空跟你硬气","roundId":"round_1782700251782_b43lslxln","userId":"uid_1781902301065_hts5zlc3s","characterId":"68071edd-2418-491e-86d1-886db71c2d5d","_id":1304},{"id":1782695863235,"sender":"them","text":"你的那些帅哥呢 怎么没陪你聊天","timestamp":1782700330810,"tempo":"N","rawContent":"你的那些帅哥呢 怎么没陪你聊天","roundId":"round_1782700251782_b43lslxln","userId":"uid_1781902301065_hts5zlc3s","characterId":"68071edd-2418-491e-86d1-886db71c2d5d","_id":1305},{"id":1782695863236,"text":"没啊 我刚吃完饭","sender":"me","time":"10:32","timestamp":1782700356453,"replyTo":null,"userId":"uid_1781902301065_hts5zlc3s","characterId":"68071edd-2418-491e-86d1-886db71c2d5d","_id":1306},{"id":1782695863237,"text":"不想跟他们聊了想跟你聊呗","sender":"me","time":"10:32","timestamp":1782700364269,"replyTo":null,"userId":"uid_1781902301065_hts5zlc3s","characterId":"68071edd-2418-491e-86d1-886db71c2d5d","_id":1307},{"id":1782695863239,"sender":"them","text":"十点半吃饭 这算哪门子饭","timestamp":1782700379115,"tempo":"N","rawContent":"十点半吃饭 这算哪门子饭","roundId":"round_1782700364336_2y3c5qm0k","userId":"uid_1781902301065_hts5zlc3s","characterId":"68071edd-2418-491e-86d1-886db71c2d5d","_id":1308},{"id":1782695863240,"sender":"them","text":"不想跟他们聊了？","timestamp":1782700381098,"tempo":"N","rawContent":"不想跟他们聊了？","roundId":"round_1782700364336_2y3c5qm0k","userId":"uid_1781902301065_hts5zlc3s","characterId":"68071edd-2418-491e-86d1-886db71c2d5d","_id":1309},{"id":1782695863241,"sender":"them","text":"怎么 被人嫌弃了跑我这找存在感了？","timestamp":1782700382599,"tempo":"N","rawContent":"怎么 被人嫌弃了跑我这找存在感了？","roundId":"round_1782700364336_2y3c5qm0k","userId":"uid_1781902301065_hts5zlc3s","characterId":"68071edd-2418-491e-86d1-886db71c2d5d","_id":1310},{"id":1782695863242,"sender":"them","text":"我可不是什么收容所","timestamp":1782700385301,"tempo":"S","rawContent":"我可不是什么收容所","roundId":"round_1782700364336_2y3c5qm0k","userId":"uid_1781902301065_hts5zlc3s","characterId":"68071edd-2418-491e-86d1-886db71c2d5d","_id":1311},{"id":1782695863243,"sender":"them","text":"不过既然你这么诚心诚意地来找我了","timestamp":1782700388815,"tempo":"N","rawContent":"不过既然你这么诚心诚意地来找我了","roundId":"round_1782700364336_2y3c5qm0k","userId":"uid_1781902301065_hts5zlc3s","characterId":"68071edd-2418-491e-86d1-886db71c2d5d","_id":1312},{"id":1782695863244,"sender":"them","text":"勉强陪你聊五块钱的","timestamp":1782700391329,"tempo":"N","rawContent":"勉强陪你聊五块钱的","roundId":"round_1782700364336_2y3c5qm0k","userId":"uid_1781902301065_hts5zlc3s","characterId":"68071edd-2418-491e-86d1-886db71c2d5d","_id":1313},{"id":1782695863245,"sender":"them","text":"吃什么了你","timestamp":1782700393094,"tempo":"N","rawContent":"吃什么了你","roundId":"round_1782700364336_2y3c5qm0k","userId":"uid_1781902301065_hts5zlc3s","characterId":"68071edd-2418-491e-86d1-886db71c2d5d","_id":1314},{"id":1782695863246,"text":"懒得跟你争 吃了小笼包啊我","sender":"me","time":"10:34","timestamp":1782700482789,"replyTo":null,"userId":"uid_1781902301065_hts5zlc3s","characterId":"68071edd-2418-491e-86d1-886db71c2d5d","_id":1315},{"id":1782695863248,"sender":"them","text":"小笼包？","timestamp":1782700496376,"tempo":"N","rawContent":"小笼包？","roundId":"round_1782700483462_uot8daf7f","userId":"uid_1781902301065_hts5zlc3s","characterId":"68071edd-2418-491e-86d1-886db71c2d5d","_id":1316},{"id":1782695863249,"sender":"them","text":"太阳打西边出来了","timestamp":1782700497483,"tempo":"N","rawContent":"太阳打西边出来了","roundId":"round_1782700483462_uot8daf7f","userId":"uid_1781902301065_hts5zlc3s","characterId":"68071edd-2418-491e-86d1-886db71c2d5d","_id":1317},{"id":1782695863250,"sender":"them","text":"今天居然没吃速冻饺子","timestamp":1782700499192,"tempo":"S","rawContent":"今天居然没吃速冻饺子","roundId":"round_1782700483462_uot8daf7f","userId":"uid_1781902301065_hts5zlc3s","characterId":"68071edd-2418-491e-86d1-886db71c2d5d","_id":1318},{"id":1782695863251,"sender":"them","text":"哪家的 外卖还是自己去买的","timestamp":1782700503059,"tempo":"N","rawContent":"哪家的 外卖还是自己去买的","roundId":"round_1782700483462_uot8daf7f","userId":"uid_1781902301065_hts5zlc3s","characterId":"68071edd-2418-491e-86d1-886db71c2d5d","_id":1319},{"id":1782695863252,"sender":"them","text":"别告诉我是你那些帅哥给你送的","timestamp":1782700505285,"tempo":"R","rawContent":"别告诉我是你那些帅哥给你送的","roundId":"round_1782700483462_uot8daf7f","userId":"uid_1781902301065_hts5zlc3s","characterId":"68071edd-2418-491e-86d1-886db71c2d5d","_id":1320},{"id":1782695863253,"text":"对呀","sender":"me","time":"10:35","timestamp":1782700530718,"replyTo":null,"userId":"uid_1781902301065_hts5zlc3s","characterId":"68071edd-2418-491e-86d1-886db71c2d5d","_id":1321},{"id":1782695863255,"sender":"them","text":"哦","timestamp":1782700542651,"tempo":"N","rawContent":"哦","roundId":"round_1782700530748_sjsg28s7z","userId":"uid_1781902301065_hts5zlc3s","characterId":"68071edd-2418-491e-86d1-886db71c2d5d","_id":1322},{"id":1782695863256,"sender":"them","text":"挺好","timestamp":1782700543500,"tempo":"R","rawContent":"挺好","roundId":"round_1782700530748_sjsg28s7z","userId":"uid_1781902301065_hts5zlc3s","characterId":"68071edd-2418-491e-86d1-886db71c2d5d","_id":1323},{"id":1782695863257,"sender":"them","text":"吃饱了就去睡觉吧","timestamp":1782700543873,"tempo":"N","rawContent":"吃饱了就去睡觉吧","roundId":"round_1782700530748_sjsg28s7z","userId":"uid_1781902301065_hts5zlc3s","characterId":"68071edd-2418-491e-86d1-886db71c2d5d","_id":1324},{"id":1782695863258,"sender":"them","text":"别在这烦我","timestamp":1782700545396,"tempo":"R","rawContent":"别在这烦我","roundId":"round_1782700530748_sjsg28s7z","userId":"uid_1781902301065_hts5zlc3s","characterId":"68071edd-2418-491e-86d1-886db71c2d5d","_id":1325},{"id":1782695863259,"text":"你咋不给我送 中饭你来给我送呗","sender":"me","time":"10:36","timestamp":1782700611855,"replyTo":null,"userId":"uid_1781902301065_hts5zlc3s","characterId":"68071edd-2418-491e-86d1-886db71c2d5d","_id":1326},{"id":1782695863261,"sender":"them","text":"我给你送？","timestamp":1782700627852,"tempo":"N","rawContent":"我给你送？","roundId":"round_1782700612644_xcyhwj4e3","userId":"uid_1781902301065_hts5zlc3s","characterId":"68071edd-2418-491e-86d1-886db71c2d5d","_id":1327},{"id":1782695863262,"sender":"them","text":"你脸可真大","timestamp":1782700629086,"tempo":"R","rawContent":"你脸可真大","roundId":"round_1782700612644_xcyhwj4e3","userId":"uid_1781902301065_hts5zlc3s","characterId":"68071edd-2418-491e-86d1-886db71c2d5d","_id":1328},{"id":1782695863263,"sender":"them","text":"我是你的外卖员吗 随叫随到","timestamp":1782700629769,"tempo":"N","rawContent":"我是你的外卖员吗 随叫随到","roundId":"round_1782700612644_xcyhwj4e3","userId":"uid_1781902301065_hts5zlc3s","characterId":"68071edd-2418-491e-86d1-886db71c2d5d","_id":1329},{"id":1782695863264,"sender":"them","text":"再说了 你的那些帅哥呢 怎么不让他们送","timestamp":1782700631910,"tempo":"S","rawContent":"再说了 你的那些帅哥呢 怎么不让他们送","roundId":"round_1782700612644_xcyhwj4e3","userId":"uid_1781902301065_hts5zlc3s","characterId":"68071edd-2418-491e-86d1-886db71c2d5d","_id":1330},{"id":1782695863265,"sender":"them","text":"不是刚有人给你送了小笼包吗 这么快就饿了","timestamp":1782700636448,"tempo":"R","rawContent":"不是刚有人给你送了小笼包吗 这么快就饿了","roundId":"round_1782700612644_xcyhwj4e3","userId":"uid_1781902301065_hts5zlc3s","characterId":"68071edd-2418-491e-86d1-886db71c2d5d","_id":1331},{"id":1782695863266,"sender":"them","text":"想让我送也行","timestamp":1782700638263,"tempo":"N","rawContent":"想让我送也行","roundId":"round_1782700612644_xcyhwj4e3","userId":"uid_1781902301065_hts5zlc3s","characterId":"68071edd-2418-491e-86d1-886db71c2d5d","_id":1332},{"id":1782695863267,"sender":"them","text":"跑腿费怎么算","timestamp":1782700639504,"tempo":"S","rawContent":"跑腿费怎么算","roundId":"round_1782700612644_xcyhwj4e3","userId":"uid_1781902301065_hts5zlc3s","characterId":"68071edd-2418-491e-86d1-886db71c2d5d","_id":1333},{"id":1782695863268,"text":"换着给我送呗","sender":"me","time":"10:37","timestamp":1782700653298,"replyTo":null,"userId":"uid_1781902301065_hts5zlc3s","characterId":"68071edd-2418-491e-86d1-886db71c2d5d","_id":1334},{"id":1782695863277,"sender":"them","text":"？","timestamp":1782700740295,"tempo":"R","rawContent":"？","roundId":"round_1782700728040_fa0c2u60o","userId":"uid_1781902301065_hts5zlc3s","characterId":"68071edd-2418-491e-86d1-886db71c2d5d","_id":1341},{"id":1782695863278,"sender":"them","text":"真当自己是海后了？","timestamp":1782700740719,"tempo":"R","rawContent":"真当自己是海后了？","roundId":"round_1782700728040_fa0c2u60o","userId":"uid_1781902301065_hts5zlc3s","characterId":"68071edd-2418-491e-86d1-886db71c2d5d","_id":1342},{"id":1782695863279,"sender":"them","text":"还换着送","timestamp":1782700741695,"tempo":"N","rawContent":"还换着送","roundId":"round_1782700728040_fa0c2u60o","userId":"uid_1781902301065_hts5zlc3s","characterId":"68071edd-2418-491e-86d1-886db71c2d5d","_id":1343},{"id":1782695863280,"sender":"them","text":"你点外卖还看心情翻牌子是吧","timestamp":1782700742838,"tempo":"N","rawContent":"你点外卖还看心情翻牌子是吧","roundId":"round_1782700728040_fa0c2u60o","userId":"uid_1781902301065_hts5zlc3s","characterId":"68071edd-2418-491e-86d1-886db71c2d5d","_id":1344},{"id":1782695863281,"sender":"them","text":"我可不跟别人凑热闹","timestamp":1782700744979,"tempo":"S","rawContent":"我可不跟别人凑热闹","roundId":"round_1782700728040_fa0c2u60o","userId":"uid_1781902301065_hts5zlc3s","characterId":"68071edd-2418-491e-86d1-886db71c2d5d","_id":1345},{"id":1782695863282,"sender":"them","text":"找你的好哥哥们继续给你送去","timestamp":1782700748318,"tempo":"N","rawContent":"找你的好哥哥们继续给你送去","roundId":"round_1782700728040_fa0c2u60o","userId":"uid_1781902301065_hts5zlc3s","characterId":"68071edd-2418-491e-86d1-886db71c2d5d","_id":1346},{"id":1782695863283,"sender":"them","text":"别来沾边","timestamp":1782700750505,"tempo":"N","rawContent":"别来沾边","roundId":"round_1782700728040_fa0c2u60o","userId":"uid_1781902301065_hts5zlc3s","characterId":"68071edd-2418-491e-86d1-886db71c2d5d","_id":1347},{"id":1782695863284,"text":"行呗行呗","sender":"me","time":"10:39","timestamp":1782700776895,"replyTo":null,"userId":"uid_1781902301065_hts5zlc3s","characterId":"68071edd-2418-491e-86d1-886db71c2d5d","_id":1348},{"id":1782695863286,"sender":"them","text":"敷衍谁呢","timestamp":1782700809423,"tempo":"R","hasThinking":true,"rawContent":"敷衍谁呢","roundId":"round_1782700777469_to96wgcgo","userId":"uid_1781902301065_hts5zlc3s","characterId":"68071edd-2418-491e-86d1-886db71c2d5d","_id":1349},{"id":1782695863287,"sender":"them","text":"就这态度还指望我给你当外卖员","timestamp":1782700810023,"tempo":"N","rawContent":"就这态度还指望我给你当外卖员","roundId":"round_1782700777469_to96wgcgo","userId":"uid_1781902301065_hts5zlc3s","characterId":"68071edd-2418-491e-86d1-886db71c2d5d","_id":1350},{"id":1782695863288,"sender":"them","text":"做梦去吧你","timestamp":1782700812559,"tempo":"N","rawContent":"做梦去吧你","roundId":"round_1782700777469_to96wgcgo","userId":"uid_1781902301065_hts5zlc3s","characterId":"68071edd-2418-491e-86d1-886db71c2d5d","_id":1351},{"id":1782695863289,"sender":"them","text":"","timestamp":1782700813632,"tempo":"N","sticker":"https://img.heliar.top/file/1771024850064_IMG_5601.jpeg","stickerMeaning":"你有意见？","rawContent":"","roundId":"round_1782700777469_to96wgcgo","userId":"uid_1781902301065_hts5zlc3s","characterId":"68071edd-2418-491e-86d1-886db71c2d5d","_id":1352},{"id":1782695863290,"sender":"them","text":"我开会去了","timestamp":1782700814236,"tempo":"S","rawContent":"我开会去了","roundId":"round_1782700777469_to96wgcgo","userId":"uid_1781902301065_hts5zlc3s","characterId":"68071edd-2418-491e-86d1-886db71c2d5d","_id":1353},{"id":1782695863291,"sender":"them","text":"自己慢慢翻你的牌子吧","timestamp":1782700816696,"tempo":"N","rawContent":"自己慢慢翻你的牌子吧","roundId":"round_1782700777469_to96wgcgo","userId":"uid_1781902301065_hts5zlc3s","characterId":"68071edd-2418-491e-86d1-886db71c2d5d","_id":1354},{"id":1782695863231,"sender":"them","text":"?","timestamp":1782700321491,"tempo":"R","rawContent":"?","roundId":"round_1782700251782_b43lslxln","userId":"uid_1781902301065_hts5zlc3s","characterId":"68071edd-2418-491e-86d1-886db71c2d5d","_id":1355},{"id":1782695863232,"sender":"them","text":"大上午的 连名带姓叫谁呢","timestamp":1782700321980,"tempo":"N","rawContent":"大上午的 连名带姓叫谁呢","roundId":"round_1782700251782_b43lslxln","userId":"uid_1781902301065_hts5zlc3s","characterId":"68071edd-2418-491e-86d1-886db71c2d5d","_id":1356},{"id":1782695863233,"sender":"them","text":"你不会一觉睡到十点半 睁眼还在记昨晚的仇吧","timestamp":1782700324126,"tempo":"R","rawContent":"你不会一觉睡到十点半 睁眼还在记昨晚的仇吧","roundId":"round_1782700251782_b43lslxln","userId":"uid_1781902301065_hts5zlc3s","characterId":"68071edd-2418-491e-86d1-886db71c2d5d","_id":1357},{"id":1782901418085,"sender":"them","text":"终于下班了","rawContent":"{\"t\":\"text\",\"s\":\"N\",\"c\":\"终于下班了\"}","content":"{\"t\":\"text\",\"s\":\"N\",\"c\":\"终于下班了\"}","timestamp":"2026-07-01T10:23:38.085Z","time":"18:23","isHtml":false,"sticker":null,"translation":null,"roundId":"round_1782901418077_qfpxcnw5c","isBackgroundMsg":true,"userId":"uid_1781902301065_hts5zlc3s","characterId":"76e6cf69-b2cd-4f98-a9e7-fc18410ba99b","_id":1358},{"id":1782901419288,"sender":"them","text":"再待下去我人都要傻了","rawContent":"{\"t\":\"text\",\"s\":\"R\",\"c\":\"再待下去我人都要傻了\"}","content":"{\"t\":\"text\",\"s\":\"R\",\"c\":\"再待下去我人都要傻了\"}","timestamp":"2026-07-01T10:23:39.288Z","time":"18:23","isHtml":false,"sticker":null,"tempo":"R","translation":null,"roundId":"round_1782901418077_qfpxcnw5c","isBackgroundMsg":true,"userId":"uid_1781902301065_hts5zlc3s","characterId":"76e6cf69-b2cd-4f98-a9e7-fc18410ba99b","_id":1359},{"id":1782901421595,"sender":"them","text":"你中午没吃 这会儿总该饿了吧","rawContent":"{\"t\":\"text\",\"s\":\"N\",\"c\":\"你中午没吃 这会儿总该饿了吧\"}","content":"{\"t\":\"text\",\"s\":\"N\",\"c\":\"你中午没吃 这会儿总该饿了吧\"}","timestamp":"2026-07-01T10:23:41.595Z","time":"18:23","isHtml":false,"sticker":null,"translation":null,"roundId":"round_1782901418077_qfpxcnw5c","isBackgroundMsg":true,"userId":"uid_1781902301065_hts5zlc3s","characterId":"76e6cf69-b2cd-4f98-a9e7-fc18410ba99b","_id":1360},{"id":1782901423268,"sender":"them","text":"我现在去买你最喜欢的那家全糖奶茶","rawContent":"{\"t\":\"text\",\"s\":\"R\",\"c\":\"我现在去买你最喜欢的那家全糖奶茶\"}","content":"{\"t\":\"text\",\"s\":\"R\",\"c\":\"我现在去买你最喜欢的那家全糖奶茶\"}","timestamp":"2026-07-01T10:23:43.268Z","time":"18:23","isHtml":false,"sticker":null,"tempo":"R","translation":null,"roundId":"round_1782901418077_qfpxcnw5c","isBackgroundMsg":true,"userId":"uid_1781902301065_hts5zlc3s","characterId":"76e6cf69-b2cd-4f98-a9e7-fc18410ba99b","_id":1361},{"id":1782901428477,"sender":"them","text":"顺便买点菜过去给你做饭？还是你想出去吃？","rawContent":"{\"t\":\"text\",\"s\":\"S\",\"c\":\"顺便买点菜过去给你做饭？还是你想出去吃？\"}","content":"{\"t\":\"text\",\"s\":\"S\",\"c\":\"顺便买点菜过去给你做饭？还是你想出去吃？\"}","timestamp":"2026-07-01T10:23:48.477Z","time":"18:23","isHtml":false,"sticker":null,"tempo":"S","translation":null,"roundId":"round_1782901418077_qfpxcnw5c","isBackgroundMsg":true,"userId":"uid_1781902301065_hts5zlc3s","characterId":"76e6cf69-b2cd-4f98-a9e7-fc18410ba99b","_id":1363},{"id":1782901368434,"text":"我吃过了呀","sender":"me","time":"18:24","timestamp":1782901469144,"replyTo":null,"reactions":[{"emoji":"🥺","roundId":"round_1782901469611_v3ro09tt9"}],"userId":"uid_1781902301065_hts5zlc3s","characterId":"76e6cf69-b2cd-4f98-a9e7-fc18410ba99b","_id":1365},{"id":1782901368436,"sender":"them","text":"？","timestamp":1782901507325,"tempo":"R","hasThinking":true,"rawContent":"？","roundId":"round_1782901469611_v3ro09tt9","userId":"uid_1781902301065_hts5zlc3s","characterId":"76e6cf69-b2cd-4f98-a9e7-fc18410ba99b","_id":1366},{"id":1782901368437,"sender":"them","text":"又背着我吃独食啊","timestamp":1782901507741,"tempo":"N","rawContent":"又背着我吃独食啊","roundId":"round_1782901469611_v3ro09tt9","userId":"uid_1781902301065_hts5zlc3s","characterId":"76e6cf69-b2cd-4f98-a9e7-fc18410ba99b","_id":1367},{"id":1782901368438,"sender":"them","text":"我刚出电梯 饿着肚子满脑子都是去超市给你买什么菜","timestamp":1782901509501,"tempo":"N","rawContent":"我刚出电梯 饿着肚子满脑子都是去超市给你买什么菜","roundId":"round_1782901469611_v3ro09tt9","userId":"uid_1781902301065_hts5zlc3s","characterId":"76e6cf69-b2cd-4f98-a9e7-fc18410ba99b","_id":1368},{"id":1782901368439,"sender":"them","text":"结果你轻飘飘一句吃过了就把我打发了... 只有我一个人在期待下班是吧","timestamp":1782901512473,"tempo":"S","rawContent":"结果你轻飘飘一句吃过了就把我打发了... 只有我一个人在期待下班是吧","roundId":"round_1782901469611_v3ro09tt9","userId":"uid_1781902301065_hts5zlc3s","characterId":"76e6cf69-b2cd-4f98-a9e7-fc18410ba99b","_id":1369},{"id":1782901368440,"sender":"them","text":"那我不管 我现在去超市买我自己的份 奶茶还是给你带","timestamp":1782901517440,"tempo":"N","rawContent":"那我不管 我现在去超市买我自己的份 奶茶还是给你带","roundId":"round_1782901469611_v3ro09tt9","userId":"uid_1781902301065_hts5zlc3s","characterId":"76e6cf69-b2cd-4f98-a9e7-fc18410ba99b","_id":1370},{"id":1782901368441,"sender":"them","text":"等下我过去做饭 你得坐在旁边陪我吃 当作补偿","timestamp":1782901520351,"tempo":"N","rawContent":"等下我过去做饭 你得坐在旁边陪我吃 当作补偿","roundId":"round_1782901469611_v3ro09tt9","userId":"uid_1781902301065_hts5zlc3s","characterId":"76e6cf69-b2cd-4f98-a9e7-fc18410ba99b","_id":1371},{"id":1782901368442,"sender":"them","text":"","timestamp":1782901523298,"tempo":"N","sticker":"https://img.heliar.top/file/1781713627011_IMG_0840.jpeg","stickerMeaning":"呜呜呜","rawContent":"","roundId":"round_1782901469611_v3ro09tt9","userId":"uid_1781902301065_hts5zlc3s","characterId":"76e6cf69-b2cd-4f98-a9e7-fc18410ba99b","_id":1372},{"id":1782901368443,"sender":"them","type":"offline_invite","text":"","offlineInvite":{"type":"this-moment","scenario":"提着购物袋在门口委屈巴巴等你开门"},"timestamp":1782901523904,"roundId":"round_1782901469611_v3ro09tt9","offlineInviteResponded":"declined","userId":"uid_1781902301065_hts5zlc3s","characterId":"76e6cf69-b2cd-4f98-a9e7-fc18410ba99b","_id":1373},{"id":1782901368444,"text":"你咋又要来我家","sender":"me","time":"18:25","timestamp":1782901526070,"replyTo":null,"userId":"uid_1781902301065_hts5zlc3s","characterId":"76e6cf69-b2cd-4f98-a9e7-fc18410ba99b","_id":1374},{"id":1782901368445,"sender":"me","type":"offline_invite_response","offlineInviteResponse":"declined","text":"","offlineInvite":{"type":"this-moment","scenario":"提着购物袋在门口委屈巴巴等你开门"},"timestamp":1782901528023,"userId":"uid_1781902301065_hts5zlc3s","characterId":"76e6cf69-b2cd-4f98-a9e7-fc18410ba99b","_id":1375},{"id":1782901368446,"text":"我还在上班啊","sender":"me","time":"18:25","timestamp":1782901531602,"replyTo":null,"userId":"uid_1781902301065_hts5zlc3s","characterId":"76e6cf69-b2cd-4f98-a9e7-fc18410ba99b","_id":1376},{"id":1782901368448,"sender":"them","text":"上班？","timestamp":1782901574115,"tempo":"R","hasThinking":true,"rawContent":"上班？","roundId":"round_1782901532365_fbptmpb2f","userId":"uid_1781902301065_hts5zlc3s","characterId":"76e6cf69-b2cd-4f98-a9e7-fc18410ba99b","_id":1377},{"id":1782901368449,"sender":"them","text":"你一个还没毕业的大学生上哪门子班 这个点还在外面？","timestamp":1782901574690,"tempo":"N","rawContent":"你一个还没毕业的大学生上哪门子班 这个点还在外面？","roundId":"round_1782901532365_fbptmpb2f","userId":"uid_1781902301065_hts5zlc3s","characterId":"76e6cf69-b2cd-4f98-a9e7-fc18410ba99b","_id":1378},{"id":1782901368450,"sender":"them","text":"是接了什么演出还是去弄你那个账号了","timestamp":1782901577614,"tempo":"N","rawContent":"是接了什么演出还是去弄你那个账号了","roundId":"round_1782901532365_fbptmpb2f","userId":"uid_1781902301065_hts5zlc3s","characterId":"76e6cf69-b2cd-4f98-a9e7-fc18410ba99b","_id":1379},{"id":1782901368451,"sender":"them","text":"在哪呢 发个定位给我呗","timestamp":1782901580432,"tempo":"S","rawContent":"在哪呢 发个定位给我呗","roundId":"round_1782901532365_fbptmpb2f","userId":"uid_1781902301065_hts5zlc3s","characterId":"76e6cf69-b2cd-4f98-a9e7-fc18410ba99b","_id":1380},{"id":1782901368452,"sender":"them","text":"既然家里不让去 那我去探班总行了吧","timestamp":1782901583648,"tempo":"N","rawContent":"既然家里不让去 那我去探班总行了吧","roundId":"round_1782901532365_fbptmpb2f","userId":"uid_1781902301065_hts5zlc3s","characterId":"76e6cf69-b2cd-4f98-a9e7-fc18410ba99b","_id":1381},{"id":1782901368453,"sender":"them","text":"刚好带着奶茶去接你下班","timestamp":1782901586558,"tempo":"N","rawContent":"刚好带着奶茶去接你下班","roundId":"round_1782901532365_fbptmpb2f","userId":"uid_1781902301065_hts5zlc3s","characterId":"76e6cf69-b2cd-4f98-a9e7-fc18410ba99b","_id":1382},{"id":1782901368454,"sender":"them","text":"","timestamp":1782901588700,"tempo":"N","sticker":"https://img.heliar.top/file/1781648226462_343cec94bp88661471ec78ba91b2b1ae.jpeg","stickerMeaning":"哎？","rawContent":"","roundId":"round_1782901532365_fbptmpb2f","userId":"uid_1781902301065_hts5zlc3s","characterId":"76e6cf69-b2cd-4f98-a9e7-fc18410ba99b","_id":1383},{"id":1782901368455,"text":"不行 我在做助教 影响不好","sender":"me","time":"18:26","timestamp":1782901606142,"replyTo":null,"userId":"uid_1781902301065_hts5zlc3s","characterId":"76e6cf69-b2cd-4f98-a9e7-fc18410ba99b","_id":1384},{"id":1782901368457,"sender":"them","text":"助教？你什么时候背着我找的活儿","timestamp":1782901636285,"tempo":"N","hasThinking":true,"rawContent":"助教？你什么时候背着我找的活儿","roundId":"round_1782901606978_u8b7w1tul","userId":"uid_1781902301065_hts5zlc3s","characterId":"76e6cf69-b2cd-4f98-a9e7-fc18410ba99b","_id":1385},{"id":1782901368458,"sender":"them","text":"不是 怎么就影响不好了","timestamp":1782901639354,"tempo":"S","rawContent":"不是 怎么就影响不好了","roundId":"round_1782901606978_u8b7w1tul","userId":"uid_1781902301065_hts5zlc3s","characterId":"76e6cf69-b2cd-4f98-a9e7-fc18410ba99b","_id":1386},{"id":1782901368459,"sender":"them","text":"我是长得见不得人 还是怕别人知道你谈恋爱了啊","timestamp":1782901643249,"tempo":"R","rawContent":"我是长得见不得人 还是怕别人知道你谈恋爱了啊","roundId":"round_1782901606978_u8b7w1tul","userId":"uid_1781902301065_hts5zlc3s","characterId":"76e6cf69-b2cd-4f98-a9e7-fc18410ba99b","_id":1387},{"id":1782901368460,"sender":"them","text":"行 既然沈老师发话了 那我肯定不进去给你添乱","timestamp":1782901645115,"tempo":"S","rawContent":"行 既然沈老师发话了 那我肯定不进去给你添乱","roundId":"round_1782901606978_u8b7w1tul","userId":"uid_1781902301065_hts5zlc3s","characterId":"76e6cf69-b2cd-4f98-a9e7-fc18410ba99b","_id":1388},{"id":1782901368461,"sender":"them","text":"我把车停远点 就在外面等你下班 这总不影响了吧","timestamp":1782901649703,"tempo":"N","rawContent":"我把车停远点 就在外面等你下班 这总不影响了吧","roundId":"round_1782901606978_u8b7w1tul","userId":"uid_1781902301065_hts5zlc3s","characterId":"76e6cf69-b2cd-4f98-a9e7-fc18410ba99b","_id":1389},{"id":1782901368462,"sender":"them","text":"几点结束？","timestamp":1782901652750,"tempo":"R","rawContent":"几点结束？","roundId":"round_1782901606978_u8b7w1tul","userId":"uid_1781902301065_hts5zlc3s","characterId":"76e6cf69-b2cd-4f98-a9e7-fc18410ba99b","_id":1390},{"id":1782901368463,"sender":"them","text":"定位还是得发我 不然我去哪接你","timestamp":1782901654058,"tempo":"N","rawContent":"定位还是得发我 不然我去哪接你","roundId":"round_1782901606978_u8b7w1tul","userId":"uid_1781902301065_hts5zlc3s","characterId":"76e6cf69-b2cd-4f98-a9e7-fc18410ba99b","_id":1391},{"id":1782901368464,"text":"都是小学生呀","sender":"me","time":"18:28","timestamp":1782901685091,"replyTo":null,"userId":"uid_1781902301065_hts5zlc3s","characterId":"76e6cf69-b2cd-4f98-a9e7-fc18410ba99b","_id":1392},{"id":1782901368466,"sticker":"https://i.postimg.cc/26TkZ8G2/27C8F086983FA7A8664DF9787A844BC8.jpg","text":"表情包：咋滴","sender":"me","time":"18:29","timestamp":1782901740703,"userId":"uid_1781902301065_hts5zlc3s","characterId":"68071edd-2418-491e-86d1-886db71c2d5d","_id":1393}]